okiti_cnt_to_cnt/__init__.py
okiti_cnt_to_cnt/okiti_cnt_to_cnt.py
okiti_cnt_to_cnt-0.0.3.dist-info/DESCRIPTION.rst
okiti_cnt_to_cnt-0.0.3.dist-info/METADATA
okiti_cnt_to_cnt-0.0.3.dist-info/RECORD
okiti_cnt_to_cnt-0.0.3.dist-info/WHEEL
okiti_cnt_to_cnt-0.0.3.dist-info/metadata.json
okiti_cnt_to_cnt-0.0.3.dist-info/top_level.txt
test/__init__.py
test/test_okiti_cnt_to_cnt.py
