Metadata-Version: 2.0
Name: okiti-cnt-to-cnt
Version: 0.0.3
Summary: Create mne readable cnt files from OKITI created ones
Home-page: https://github.com/bbaattaahh/okiti_cnt_to_cnt2
Author: bbaattaahh
Author-email: bbaattaahh@gmail.com
License: UNKNOWN
Platform: UNKNOWN
Classifier: Programming Language :: Python :: 3
Classifier: License :: OSI Approved :: MIT License
Classifier: Operating System :: OS Independent
